nyt_books_sdk/__init__.py
nyt_books_sdk/sdk.py
nyt_books_sdk/hooks/__init__.py
nyt_books_sdk/hooks/hook.py
nyt_books_sdk/models/__init__.py
nyt_books_sdk/models/base.py
nyt_books_sdk/models/get_lists_best_sellers_history_json_ok_response.py
nyt_books_sdk/models/get_lists_date_list_json_ok_response.py
nyt_books_sdk/models/get_lists_format_ok_response.py
nyt_books_sdk/models/get_lists_names_format_ok_response.py
nyt_books_sdk/models/get_reviews_format_ok_response.py
nyt_books_sdk/models/overview_response.py
nyt_books_sdk/models/result.py
nyt_books_sdk/models/utils/cast_models.py
nyt_books_sdk/models/utils/json_map.py
nyt_books_sdk/net/__init__.py
nyt_books_sdk/net/environment/__init__.py
nyt_books_sdk/net/environment/environment.py
nyt_books_sdk/net/headers/__init__.py
nyt_books_sdk/net/headers/base_header.py
nyt_books_sdk/net/request_chain/__init__.py
nyt_books_sdk/net/request_chain/request_chain.py
nyt_books_sdk/net/request_chain/handlers/__init__.py
nyt_books_sdk/net/request_chain/handlers/base_handler.py
nyt_books_sdk/net/request_chain/handlers/hook_handler.py
nyt_books_sdk/net/request_chain/handlers/http_handler.py
nyt_books_sdk/net/request_chain/handlers/retry_handler.py
nyt_books_sdk/net/transport/__init__.py
nyt_books_sdk/net/transport/request.py
nyt_books_sdk/net/transport/request_error.py
nyt_books_sdk/net/transport/response.py
nyt_books_sdk/net/transport/serializer.py
nyt_books_sdk/net/transport/utils.py
nyt_books_sdk/services/__init__.py
nyt_books_sdk/services/lists.py
nyt_books_sdk/services/lists_json.py
nyt_books_sdk/services/reviews_json.py
nyt_books_sdk/services/utils/base_service.py
nyt_books_sdk/services/utils/default_headers.py
nyt_books_sdk/services/utils/validator.py
nyt_books-1.0.0.dist-info/LICENSE
nyt_books-1.0.0.dist-info/METADATA
nyt_books-1.0.0.dist-info/WHEEL
nyt_books-1.0.0.dist-info/top_level.txt
nyt_books-1.0.0.dist-info/RECORD
