Metadata-Version: 2.1
Name: nyt-books
Version: 1.0.0
Summary: The Books API provides information about book reviews and The New York Times Best Sellers lists.
License: MIT
Requires-Python: >=3.7
License-File: LICENSE
Requires-Dist: requests >=2.31.0
